cognix/__init__.py
cognix/cli.py
cognix/config.py
cognix/context.py
cognix/diff_engine.py
cognix/error_handling.py
cognix/llm.py
cognix/main.py
cognix/memory.py
cognix/prompt_templates.py
cognix/reference_parser.py
cognix/related_finder.py
cognix/run.py
cognix/session.py
cognix/utils.py
cognix-0.1.5.dist-info/licenses/LICENSE
cognix-0.1.5.dist-info/METADATA
cognix-0.1.5.dist-info/WHEEL
cognix-0.1.5.dist-info/entry_points.txt
cognix-0.1.5.dist-info/top_level.txt
cognix-0.1.5.dist-info/RECORD
