Metadata-Version: 2.4
Name: cognix
Version: 0.1.5
Summary: AI-powered CLI development assistant
Author: Cognix
Maintainer: Cognix
License-Expression: MIT
Requires-Python: >=3.9
License-File: LICENSE
Requires-Dist: openai>=1.0.0
Requires-Dist: anthropic>=0.5.0
Requires-Dist: pydantic>=1.10.0
Requires-Dist: rich>=13.0.0
Requires-Dist: colorama>=0.4.6
Requires-Dist: python-dotenv>=1.0.0
Requires-Dist: toml>=0.10.2
Requires-Dist: typing-extensions>=4.7.0
Requires-Dist: pytest>=7.0.0
Provides-Extra: dev
Requires-Dist: black>=23.0.0; extra == "dev"
Requires-Dist: flake8>=6.0.0; extra == "dev"
Dynamic: license-file
